cosipy/__init__.py
cosipy/_version.py
cosipy/background_estimation/ContinuumEstimation.py
cosipy/background_estimation/LineBackgroundEstimation.py
cosipy/background_estimation/__init__.py
cosipy/data_io/BinnedData.py
cosipy/data_io/DataIO.py
cosipy/data_io/ReadTraTest.py
cosipy/data_io/UnBinnedData.py
cosipy/data_io/__init__.py
cosipy/image_deconvolution/RichardsonLucy.py
cosipy/image_deconvolution/RichardsonLucySimple.py
cosipy/image_deconvolution/__init__.py
cosipy/image_deconvolution/allskyimage.py
cosipy/image_deconvolution/coordsys_conversion_matrix.py
cosipy/image_deconvolution/dataIF_COSI_DC2.py
cosipy/image_deconvolution/deconvolution_algorithm_base.py
cosipy/image_deconvolution/exposure_table.py
cosipy/image_deconvolution/image_deconvolution.py
cosipy/image_deconvolution/image_deconvolution_data_interface_base.py
cosipy/image_deconvolution/model_base.py
cosipy/polarization/__init__.py
cosipy/polarization/conventions.py
cosipy/polarization/polarization_angle.py
cosipy/polarization/polarization_asad.py
cosipy/response/DetectorResponse.py
cosipy/response/ExtendedSourceResponse.py
cosipy/response/FullDetectorResponse.py
cosipy/response/PointSourceResponse.py
cosipy/response/__init__.py
cosipy/response/functions.py
cosipy/source_injector/__init__.py
cosipy/source_injector/source_injector.py
cosipy/spacecraftfile/SpacecraftFile.py
cosipy/spacecraftfile/__init__.py
cosipy/spacecraftfile/scatt_map.py
cosipy/test_data/__init__.py
cosipy/threeml/COSILike.py
cosipy/threeml/__init__.py
cosipy/threeml/custom_functions.py
cosipy/ts_map/TSMap.py
cosipy/ts_map/__init__.py
cosipy/ts_map/fast_norm_fit.py
cosipy/ts_map/fast_ts_fit.py
cosipy/util/__init__.py
cosipy/util/data_fetching.py
cosipy-0.3.4.dist-info/licenses/LICENSE
cosipy-0.3.4.dist-info/METADATA
cosipy-0.3.4.dist-info/WHEEL
cosipy-0.3.4.dist-info/entry_points.txt
cosipy-0.3.4.dist-info/top_level.txt
cosipy-0.3.4.dist-info/RECORD
