Metadata-Version: 2.4
Name: cosipy
Version: 0.3.4
Summary: High-level analysis for the COSI telescope data
Home-page: https://github.com/cositools/cosipy
Author: COSI Team
Author-email: imc@umd.edu
License-File: LICENSE
Requires-Dist: histpy<2
Requires-Dist: mhealpy
Requires-Dist: scoords
Requires-Dist: astromodels>=2.4.2
Requires-Dist: threeml>=2.1.2
Requires-Dist: matplotlib<=3.8.3
Requires-Dist: numba
Requires-Dist: astropy>5.0
Requires-Dist: yayc
Requires-Dist: awscli
Requires-Dist: scipy<=1.13.0
Dynamic: author
Dynamic: author-email
Dynamic: description
Dynamic: description-content-type
Dynamic: home-page
Dynamic: license-file
Dynamic: requires-dist
Dynamic: summary
